Metadata-Version: 2.1
Name: telegram-shell-notifier
Version: 0.2
Summary: Simple telegram notifier, ready for shell usage
Home-page: http://github.com/airens/telegram_notifier
Author: Valeriy Chistyakov
Author-email: airens@mail.ru
License: MIT
Platform: UNKNOWN
